conf/__init__.py
conf/property.py
conf/setting.py
exception/__init__.py
exception/exceptions.py
resources/__init__.py
resources/db_setting.py
resources/setting.py
resources/debug/__init__.py
resources/debug/db_setting.py
resources/debug/setting.py
resources/dev/__init__.py
resources/dev/db_setting.py
resources/dev/setting.py
resources/local/__init__.py
resources/local/db_setting.py
resources/local/setting.py
resources/local_to_dev/__init__.py
resources/local_to_dev/db_setting.py
resources/local_to_dev/setting.py
resources/local_to_prod/__init__.py
resources/local_to_prod/db_setting.py
resources/local_to_prod/setting.py
resources/prod/__init__.py
resources/prod/db_setting.py
resources/prod/setting.py
shino/__init__.py
shino/check.py
shino/gentable.py
shino/cleaner/__init__.py
shino/cleaner/__main__.py
shino/cleaner/clean_handle.py
shino/cleaner/clean_processor.py
shino/downloader/__init__.py
shino/downloader/__main__.py
shino/downloader/download_handle.py
shino/downloader/download_processor.py
shino/downloader/middleware_manager.py
shino/downloader/downloader/__init__.py
shino/downloader/downloader/downloader.py
shino/downloader/downloader/simple.py
shino/downloader/middleware/__init__.py
shino/downloader/middleware/check.py
shino/downloader/middleware/default.py
shino/downloader/middleware/headers.py
shino/downloader/middleware/useragent.py
shino/extractor/__init__.py
shino/extractor/__main__.py
shino/extractor/extract_handle.py
shino/extractor/extract_processor.py
shino/libs/__init__.py
shino/libs/encrypt.py
shino/libs/fetch.py
shino/libs/load.py
shino/libs/log_ext.py
shino/libs/misc.py
shino/libs/mongo_ext.py
shino/libs/mysql_ext.py
shino/libs/python.py
shino/libs/rabbitmq_ext.py
shino/libs/sqlalchemy_ext.py
shino/libs/time_ext.py
shino/libs/url.py
shino/saver/__init__.py
shino/saver/__main__.py
shino/saver/save_handle.py
shino/saver/save_processor.py
shino/seed_generator/__init__.py
shino/seed_generator/__main__.py
shino/seed_generator/dynamic_url.py
shino-0.0.1.dist-info/LICENSE
shino-0.0.1.dist-info/METADATA
shino-0.0.1.dist-info/WHEEL
shino-0.0.1.dist-info/entry_points.txt
shino-0.0.1.dist-info/top_level.txt
shino-0.0.1.dist-info/RECORD
