Metadata-Version: 2.1
Name: shino
Version: 0.0.1
Summary: common spider
Home-page: https://github.com/hacksman/shino
Author: hacksman
Author-email: funblessu@gmail.com
License: MIT
Platform: UNKNOWN
Classifier: License :: OSI Approved :: MIT License
Classifier: Programming Language :: Python :: 3
Classifier: Programming Language :: Python :: 3.7
License-File: LICENSE
Requires-Dist: requests
Requires-Dist: loguru
Requires-Dist: retrying
Requires-Dist: pymysql
Requires-Dist: dbutils
Requires-Dist: glom
Requires-Dist: redis
Requires-Dist: furl
Requires-Dist: arrow
Requires-Dist: pytz
Requires-Dist: grpcio-tools
Requires-Dist: kombu
Requires-Dist: croniter
Requires-Dist: schedule
Requires-Dist: cryptography
Requires-Dist: lxml
Requires-Dist: stringcase
Requires-Dist: sqlalchemy
Requires-Dist: pymongo
Requires-Dist: amqp
